{
  "name": "Impulsionando · retencao · cancelamento-solicitado",
  "meta": {
    "generated_by": "docs/n8n/generate-workflows.mjs",
    "workflow_id": 36,
    "regua": "retencao",
    "slug": "cancelamento-solicitado",
    "plano_min": "essencial",
    "canais": [
      "internal",
      "email"
    ],
    "gatilho": "cancel.requested",
    "status": "rascunho",
    "mode_default": "demo"
  },
  "nodes": [
    {
      "id": "webhook",
      "name": "Webhook · cancelamento-solicitado",
      "type": "n8n-nodes-base.webhook",
      "typeVersion": 2,
      "position": [
        240,
        300
      ],
      "parameters": {
        "httpMethod": "POST",
        "path": "impulsionando/{{tenant_slug}}/cancelamento-solicitado",
        "responseMode": "responseNode",
        "options": {}
      }
    },
    {
      "id": "mode-gate",
      "name": "Mode Gate (demo vs producao)",
      "type": "n8n-nodes-base.if",
      "typeVersion": 2,
      "position": [
        440,
        300
      ],
      "parameters": {
        "conditions": {
          "options": {
            "caseSensitive": true,
            "typeValidation": "loose"
          },
          "conditions": [
            {
              "id": "mode",
              "leftValue": "={{$json.body.mode}}",
              "rightValue": "producao",
              "operator": {
                "type": "string",
                "operation": "equals"
              }
            }
          ],
          "combinator": "and"
        }
      }
    },
    {
      "id": "simulate",
      "name": "Simulate (demo)",
      "type": "n8n-nodes-base.set",
      "typeVersion": 3,
      "position": [
        640,
        180
      ],
      "parameters": {
        "assignments": {
          "assignments": [
            {
              "id": "status",
              "name": "status",
              "value": "skipped",
              "type": "string"
            },
            {
              "id": "note",
              "name": "note",
              "value": "demo: no real dispatch for cancelamento-solicitado",
              "type": "string"
            }
          ]
        },
        "options": {}
      }
    },
    {
      "id": "validate",
      "name": "Validate tenant/canal/template",
      "type": "n8n-nodes-base.code",
      "typeVersion": 2,
      "position": [
        640,
        420
      ],
      "parameters": {
        "language": "javaScript",
        "jsCode": "const b = $json.body || $json;\nconst errors = [];\nif (!b?.tenant?.id) errors.push('tenant.id ausente');\nif (!b?.consent?.lgpd_ok) errors.push('consent.lgpd_ok=false');\nconst canais = [\"internal\",\"email\"];\nfor (const c of canais) {\n  if (c === 'internal' || c === 'impulsionito') continue;\n  if (!b?.channels?.[c]?.enabled) errors.push(`canal ${c} desabilitado`);\n  if (!b?.channels?.[c]?.template_id) errors.push(`template ${c} ausente`);\n}\nreturn [{ json: { ...b, _validation: { ok: errors.length === 0, errors } } }];"
      }
    },
    {
      "id": "channel-internal",
      "name": "Notificação interna [demo:disabled]",
      "type": "n8n-nodes-base.httpRequest",
      "typeVersion": 4,
      "position": [
        840,
        420
      ],
      "disabled": true,
      "parameters": {
        "method": "POST",
        "url": "={{$env.IMPULSIONANDO_API_BASE}}/api/public/hooks/notify-staff",
        "sendHeaders": true,
        "headerParameters": {
          "parameters": [
            {
              "name": "Content-Type",
              "value": "application/json"
            }
          ]
        },
        "jsonBody": "={{ JSON.stringify({ tenant: $json.tenant, entity: $json.entity, template_id: $json.channels?.internal?.template_id, payload: $json.context }) }}",
        "options": {
          "timeout": 15000
        }
      }
    },
    {
      "id": "channel-email",
      "name": "E-mail (Resend) [demo:disabled]",
      "type": "n8n-nodes-base.httpRequest",
      "typeVersion": 4,
      "position": [
        880,
        420
      ],
      "disabled": true,
      "parameters": {
        "method": "POST",
        "url": "https://api.resend.com/emails",
        "sendHeaders": true,
        "headerParameters": {
          "parameters": [
            {
              "name": "Content-Type",
              "value": "application/json"
            }
          ]
        },
        "jsonBody": "={{ JSON.stringify({ tenant: $json.tenant, entity: $json.entity, template_id: $json.channels?.email?.template_id, payload: $json.context }) }}",
        "options": {
          "timeout": 15000
        }
      }
    },
    {
      "id": "log",
      "name": "Log → /api/public/hooks/n8n-log",
      "type": "n8n-nodes-base.httpRequest",
      "typeVersion": 4,
      "position": [
        1240,
        300
      ],
      "parameters": {
        "method": "POST",
        "url": "={{$env.IMPULSIONANDO_API_BASE}}/api/public/hooks/n8n-log",
        "sendHeaders": true,
        "headerParameters": {
          "parameters": [
            {
              "name": "x-impulsionando-signature",
              "value": "={{$crypto.createHmac('sha256', $env.IMPULSIONANDO_WEBHOOK_SECRET).update(JSON.stringify($json)).digest('hex')}}"
            },
            {
              "name": "Content-Type",
              "value": "application/json"
            }
          ]
        },
        "jsonBody": "={{ JSON.stringify({ workflow_name: 'cancelamento-solicitado', workflow_version: '1.0.0', regua: 'retencao', event_name: 'cancel.requested', step: 'complete', status: ($json._validation?.ok === false ? 'failed' : ($json.status || 'ok')), tenant_id: $json.tenant?.id, entity_type: $json.entity?.type, entity_id: $json.entity?.id, payload: $json, idempotency_key: 'cancelamento-solicitado:' + ($json.tenant?.slug || 'demo') + ':' + ($json.entity?.id || $now) }) }}",
        "options": {
          "timeout": 15000
        }
      }
    },
    {
      "id": "fallback",
      "name": "Fallback humano",
      "type": "n8n-nodes-base.httpRequest",
      "typeVersion": 4,
      "position": [
        1240,
        540
      ],
      "disabled": true,
      "parameters": {
        "method": "POST",
        "url": "={{$env.IMPULSIONANDO_API_BASE}}/api/public/hooks/notify-staff",
        "sendHeaders": true,
        "headerParameters": {
          "parameters": [
            {
              "name": "Content-Type",
              "value": "application/json"
            }
          ]
        },
        "jsonBody": "={{ JSON.stringify({ workflow: 'cancelamento-solicitado', tenant: $json.tenant, error: $json.error || 'unknown', regua: 'retencao' }) }}",
        "options": {
          "timeout": 15000
        }
      }
    },
    {
      "id": "respond",
      "name": "Respond 200",
      "type": "n8n-nodes-base.respondToWebhook",
      "typeVersion": 1,
      "position": [
        1440,
        300
      ],
      "parameters": {
        "respondWith": "json",
        "responseBody": "={{ JSON.stringify({ ok: true, workflow: 'cancelamento-solicitado', mode: $json.body?.mode || $json.mode || 'demo' }) }}"
      }
    }
  ],
  "connections": {
    "Webhook · cancelamento-solicitado": {
      "main": [
        [
          {
            "node": "Mode Gate (demo vs producao)",
            "type": "main",
            "index": 0
          }
        ]
      ]
    },
    "Mode Gate (demo vs producao)": {
      "main": [
        [
          {
            "node": "Validate tenant/canal/template",
            "type": "main",
            "index": 0
          }
        ],
        [
          {
            "node": "Simulate (demo)",
            "type": "main",
            "index": 0
          }
        ]
      ]
    },
    "Validate tenant/canal/template": {
      "main": [
        [
          {
            "node": "Notificação interna [demo:disabled]",
            "type": "main",
            "index": 0
          },
          {
            "node": "E-mail (Resend) [demo:disabled]",
            "type": "main",
            "index": 0
          }
        ]
      ]
    },
    "Notificação interna [demo:disabled]": {
      "main": [
        [
          {
            "node": "Log → /api/public/hooks/n8n-log",
            "type": "main",
            "index": 0
          }
        ]
      ]
    },
    "E-mail (Resend) [demo:disabled]": {
      "main": [
        [
          {
            "node": "Log → /api/public/hooks/n8n-log",
            "type": "main",
            "index": 0
          }
        ]
      ]
    },
    "Simulate (demo)": {
      "main": [
        [
          {
            "node": "Log → /api/public/hooks/n8n-log",
            "type": "main",
            "index": 0
          }
        ]
      ]
    },
    "Log → /api/public/hooks/n8n-log": {
      "main": [
        [
          {
            "node": "Respond 200",
            "type": "main",
            "index": 0
          }
        ]
      ]
    }
  },
  "active": false,
  "settings": {
    "executionOrder": "v1"
  },
  "tags": [
    {
      "name": "impulsionando"
    },
    {
      "name": "retencao"
    },
    {
      "name": "core"
    }
  ]
}
